development/__init__.py
development/normalize_sandbox_fusion.py
development/utils/__init__.py
development/utils/generate_api_key.py
development/utils/subprocess_manager.py
examples/__init__.py
examples/braintrust_integration.py
examples/e2b_auto_extract_example.py
examples/e2b_fallback_example.py
examples/e2b_javascript_example.py
examples/e2b_reward_example.py
examples/n_variant_to_batch_demo.py
examples/rollout_control_plane_demo.py
examples/test_unified_framework_final.py
examples/test_unified_servers.py
examples/frozen_lake_mcp/__init__.py
examples/frozen_lake_mcp/frozen_lake_adapter.py
examples/frozen_lake_mcp/frozen_lake_mcp.py
examples/frozen_lake_mcp/frozen_lake_mcp_simplified.py
examples/frozen_lake_mcp/rollout_example.py
examples/frozen_lake_mcp/server.py
examples/frozen_lake_mcp/test_basic_functionality.py
examples/frozen_lake_mcp/test_north_star.py
examples/frozen_lake_mcp/test_rollout_termination.py
examples/frozen_lake_mcp/test_termination_fix.py
examples/test_tasks/__init__.py
examples/test_tasks/reward.py
examples/test_tasks/tools.py
examples/trl_integration/__init__.py
examples/trl_integration/convert_dataset_to_jsonl.py
examples/trl_integration/grpo_example.py
examples/trl_integration/minimal_deepcoder_grpo_example.py
examples/trl_integration/ppo_example.py
examples/trl_integration/test_trl_integration.py
examples/trl_integration/trl_adapter.py
examples/trl_integration/working_grpo_example.py
reward_kit/__init__.py
reward_kit/__main__.py
reward_kit/_version.py
reward_kit/auth.py
reward_kit/cli.py
reward_kit/common_utils.py
reward_kit/config.py
reward_kit/evaluation.py
reward_kit/gcp_tools.py
reward_kit/generic_server.py
reward_kit/mcp_env.py
reward_kit/models.py
reward_kit/packaging.py
reward_kit/platform_api.py
reward_kit/playback_policy.py
reward_kit/resources.py
reward_kit/reward_function.py
reward_kit/rl_processing.py
reward_kit/server.py
reward_kit/typed_interface.py
reward_kit/adapters/__init__.py
reward_kit/adapters/braintrust.py
reward_kit-0.3.6.dist-info/licenses/LICENSE
reward_kit-0.3.6.dist-info/METADATA
reward_kit-0.3.6.dist-info/WHEEL
reward_kit-0.3.6.dist-info/entry_points.txt
reward_kit-0.3.6.dist-info/top_level.txt
reward_kit-0.3.6.dist-info/RECORD
