Metadata-Version: 2.4
Name: reward-kit
Version: 0.3.6
Summary: A Python library for defining, testing, and using reward functions
Home-page: https://github.com/fireworks-ai/reward-kit
Author: Fireworks AI
Author-email: info@fireworks.ai
Classifier: Programming Language :: Python :: 3
Classifier: License :: OSI Approved :: Apache Software License
Classifier: Operating System :: OS Independent
Requires-Python: >=3.10
License-File: LICENSE
Requires-Dist: requests>=2.25.0
Requires-Dist: pydantic>=2.0.0
Requires-Dist: dataclasses-json>=0.5.7
Requires-Dist: fastapi>=0.68.0
Requires-Dist: uvicorn>=0.15.0
Requires-Dist: python-dotenv>=0.19.0
Requires-Dist: openai==1.78.1
Requires-Dist: aiosqlite
Requires-Dist: aiohttp
Requires-Dist: mcp>=1.9.2
Requires-Dist: PyYAML>=5.0
Requires-Dist: datasets==3.6.0
Requires-Dist: fsspec==2025.3.0
Requires-Dist: hydra-core>=1.3.2
Requires-Dist: omegaconf>=2.3.0
Requires-Dist: gymnasium>=0.29.0
Requires-Dist: httpx>=0.24.0
Requires-Dist: fireworks-ai>=0.17.19
Provides-Extra: dev
Requires-Dist: build; extra == "dev"
Requires-Dist: twine; extra == "dev"
Requires-Dist: pytest>=6.0.0; extra == "dev"
Requires-Dist: pytest-asyncio; extra == "dev"
Requires-Dist: pytest-httpserver; extra == "dev"
Requires-Dist: werkzeug>=2.0.0; extra == "dev"
Requires-Dist: black>=21.5b2; extra == "dev"
Requires-Dist: mypy>=0.812; extra == "dev"
Requires-Dist: flake8>=3.9.2; extra == "dev"
Requires-Dist: autopep8>=1.5.0; extra == "dev"
Requires-Dist: transformers>=4.0.0; extra == "dev"
Requires-Dist: types-setuptools; extra == "dev"
Requires-Dist: types-requests; extra == "dev"
Requires-Dist: types-PyYAML; extra == "dev"
Requires-Dist: types-docker; extra == "dev"
Requires-Dist: versioneer>=0.20; extra == "dev"
Requires-Dist: openai==1.78.1; extra == "dev"
Requires-Dist: pre-commit; extra == "dev"
Requires-Dist: e2b>=0.15.0; extra == "dev"
Requires-Dist: docker==7.1.0; extra == "dev"
Provides-Extra: trl
Requires-Dist: torch>=1.9; extra == "trl"
Requires-Dist: trl>=0.7.0; extra == "trl"
Requires-Dist: peft>=0.7.0; extra == "trl"
Requires-Dist: transformers>=4.0.0; extra == "trl"
Requires-Dist: accelerate>=0.28.0; extra == "trl"
Provides-Extra: deepseek
Requires-Dist: difflib>=3.0.0; extra == "deepseek"
Provides-Extra: openevals
Requires-Dist: openevals>=0.1.0; extra == "openevals"
Dynamic: author
Dynamic: author-email
Dynamic: classifier
Dynamic: description
Dynamic: home-page
Dynamic: license-file
Dynamic: provides-extra
Dynamic: requires-dist
Dynamic: requires-python
Dynamic: summary
